neoval_py_utils/__init__.py
neoval_py_utils/exporter.py
neoval_py_utils/ipdb.py
neoval_py_utils/ipdb_build_event.py
neoval_py_utils/ipdb_builder.py
neoval_py_utils/template.py
neoval_py_utils/utils.py
neoval_py_utils-0.5.1.dist-info/METADATA
neoval_py_utils-0.5.1.dist-info/WHEEL
neoval_py_utils-0.5.1.dist-info/entry_points.txt
neoval_py_utils-0.5.1.dist-info/RECORD
