Metadata-Version: 2.3
Name: neoval-py-utils
Version: 0.5.1
Summary: 
Author: Neoval
Author-email: data@neoval.io
Requires-Python: >=3.10,<3.13
Classifier: Programming Language :: Python :: 3
Classifier: Programming Language :: Python :: 3.10
Classifier: Programming Language :: Python :: 3.11
Classifier: Programming Language :: Python :: 3.12
Requires-Dist: duckdb (==1.*)
Requires-Dist: google-cloud-bigquery
Requires-Dist: google-cloud-storage
Requires-Dist: jinja2 (>=3.1.2,<4.0.0)
Requires-Dist: polars
Requires-Dist: pyarrow
Requires-Dist: pyyaml (>=6.0.1,<7.0.0)
Requires-Dist: taskipy (>=1.12.2,<2.0.0)
Requires-Dist: typer (==0.*)
